<?xml version="1.0" encoding="utf-8" ?>
<dwsync>
<file name="Chart.php" server="ftp.adwaitpande.in:3214/public_html/dev/DES/" local="130527253940000000" remote="131386861050000000" Dst="0" />
<file name="Comments.php" server="ftp.adwaitpande.in:3214/public_html/dev/DES/" local="130527253940000000" remote="131386861060000000" Dst="0" />
<file name="ContentTypes.php" server="ftp.adwaitpande.in:3214/public_html/dev/DES/" local="130527253940000000" remote="131386861070000000" Dst="0" />
<file name="DocProps.php" server="ftp.adwaitpande.in:3214/public_html/dev/DES/" local="130527253940000000" remote="131386861080000000" Dst="0" />
<file name="Drawing.php" server="ftp.adwaitpande.in:3214/public_html/dev/DES/" local="130527253940000000" remote="131386861100000000" Dst="0" />
<file name="Rels.php" server="ftp.adwaitpande.in:3214/public_html/dev/DES/" local="130527253940000000" remote="131386861110000000" Dst="0" />
<file name="RelsRibbon.php" server="ftp.adwaitpande.in:3214/public_html/dev/DES/" local="130527253940000000" remote="131386861120000000" Dst="0" />
<file name="RelsVBA.php" server="ftp.adwaitpande.in:3214/public_html/dev/DES/" local="130527253940000000" remote="131386861130000000" Dst="0" />
<file name="StringTable.php" server="ftp.adwaitpande.in:3214/public_html/dev/DES/" local="130527253940000000" remote="131386861140000000" Dst="0" />
<file name="Style.php" server="ftp.adwaitpande.in:3214/public_html/dev/DES/" local="130527253940000000" remote="131386861150000000" Dst="0" />
<file name="Theme.php" server="ftp.adwaitpande.in:3214/public_html/dev/DES/" local="130527253940000000" remote="131386861160000000" Dst="0" />
<file name="Workbook.php" server="ftp.adwaitpande.in:3214/public_html/dev/DES/" local="130527253940000000" remote="131386861170000000" Dst="0" />
<file name="Worksheet.php" server="ftp.adwaitpande.in:3214/public_html/dev/DES/" local="130527253940000000" remote="131386861190000000" Dst="0" />
<file name="WriterPart.php" server="ftp.adwaitpande.in:3214/public_html/dev/DES/" local="130527253940000000" remote="131386861200000000" Dst="0" />
</dwsync>